instabotClub/__init__.py
instabotClub/__main__.py
instabotClub/version.py
instabotClub/core/__init__.py
instabotClub/core/bot_flow.py
instabotClub/core/config.py
instabotClub/core/decorators.py
instabotClub/core/device_facade.py
instabotClub/core/download_from_github.py
instabotClub/core/filter.py
instabotClub/core/handle_sources.py
instabotClub/core/interaction.py
instabotClub/core/log.py
instabotClub/core/navigation.py
instabotClub/core/persistent_list.py
instabotClub/core/plugin_loader.py
instabotClub/core/report.py
instabotClub/core/resources.py
instabotClub/core/scroll_end_detector.py
instabotClub/core/session_state.py
instabotClub/core/storage.py
instabotClub/core/utils.py
instabotClub/core/views.py
instabotClub/plugins/__init__.py
instabotClub/plugins/action_unfollow_followers.py
instabotClub/plugins/cloned_app.py
instabotClub/plugins/core_arguments.py
instabotClub/plugins/data_analytics.py
instabotClub/plugins/interact_blogger.py
instabotClub/plugins/interact_blogger_followers.py
instabotClub/plugins/interact_blogger_post_likers.py
instabotClub/plugins/interact_feed.py
instabotClub/plugins/interact_hashtag_likers.py
instabotClub/plugins/interact_hashtag_posts.py
instabotClub/plugins/interact_place_likers.py
instabotClub/plugins/interact_place_posts.py
instabotClub/plugins/like_from_urls.py
instabotClub/plugins/remove_followers.py
instabotClub/plugins/telegram.py
instabotClub-3.2.1.dist-info/LICENSE
instabotClub-3.2.1.dist-info/METADATA
instabotClub-3.2.1.dist-info/WHEEL
instabotClub-3.2.1.dist-info/entry_points.txt
instabotClub-3.2.1.dist-info/top_level.txt
instabotClub-3.2.1.dist-info/RECORD
