Metadata-Version: 2.1
Name: instabotClub
Version: 3.2.1
Summary: Thank you for using instabotClub tool, if you encounter an error during use, please contact me: Email: instabotclub@gmail.com. Do not resell this tool without the consent of instabotClub!. Programmed in Python and compatible with basically any android device that can run instagram - real or emulated.
Home-page: https://github.com/instabotClub/bot/
Author: instabotClub Team
Author-email: instabotclub@gmail.com
License: UNKNOWN
Platform: UNKNOWN
Classifier: Programming Language :: Python :: 3.6
Classifier: Programming Language :: Python :: 3.7
Classifier: Programming Language :: Python :: 3.8
Classifier: Programming Language :: Python :: 3.9
Classifier: Operating System :: OS Independent
Requires-Python: >=3.6
License-File: LICENSE
Requires-Dist: colorama (==0.4.4)
Requires-Dist: ConfigArgParse (==1.5.3)
Requires-Dist: PyYAML (==6.0)
Requires-Dist: uiautomator2 (==2.16.14)
Requires-Dist: urllib3 (==1.26.7)
Requires-Dist: emoji (==1.6.1)
Requires-Dist: langdetect (==1.0.9)
Requires-Dist: atomicwrites (==1.4.0)
Requires-Dist: spintax (==1.0.4)
Provides-Extra: analytics
Requires-Dist: matplotlib (==3.4.2) ; extra == 'analytics'
Provides-Extra: telegram-reports
Requires-Dist: pandas (==1.2.4) ; extra == 'telegram-reports'
